persian_converter/__init__.py
persian_converter/converter.py
PersianConverter-1.0.11.dist-info/METADATA
PersianConverter-1.0.11.dist-info/WHEEL
PersianConverter-1.0.11.dist-info/entry_points.txt
PersianConverter-1.0.11.dist-info/top_level.txt
PersianConverter-1.0.11.dist-info/RECORD
